ask_smapi_model/__init__.py
ask_smapi_model/__version__.py
ask_smapi_model/py.typed
ask_smapi_model/services/__init__.py
ask_smapi_model/services/py.typed
ask_smapi_model/services/skill_management/__init__.py
ask_smapi_model/services/skill_management/py.typed
ask_smapi_model/services/skill_management/skill_management_service_client.py
ask_smapi_model/v0/__init__.py
ask_smapi_model/v0/bad_request_error.py
ask_smapi_model/v0/error.py
ask_smapi_model/v0/py.typed
ask_smapi_model/v0/catalog/__init__.py
ask_smapi_model/v0/catalog/catalog_details.py
ask_smapi_model/v0/catalog/catalog_summary.py
ask_smapi_model/v0/catalog/catalog_type.py
ask_smapi_model/v0/catalog/catalog_usage.py
ask_smapi_model/v0/catalog/create_catalog_request.py
ask_smapi_model/v0/catalog/list_catalogs_response.py
ask_smapi_model/v0/catalog/py.typed
ask_smapi_model/v0/catalog/upload/__init__.py
ask_smapi_model/v0/catalog/upload/complete_upload_request.py
ask_smapi_model/v0/catalog/upload/content_upload_file_summary.py
ask_smapi_model/v0/catalog/upload/content_upload_summary.py
ask_smapi_model/v0/catalog/upload/create_content_upload_request.py
ask_smapi_model/v0/catalog/upload/create_content_upload_response.py
ask_smapi_model/v0/catalog/upload/file_upload_status.py
ask_smapi_model/v0/catalog/upload/get_content_upload_response.py
ask_smapi_model/v0/catalog/upload/ingestion_status.py
ask_smapi_model/v0/catalog/upload/ingestion_step_name.py
ask_smapi_model/v0/catalog/upload/list_uploads_response.py
ask_smapi_model/v0/catalog/upload/pre_signed_url_item.py
ask_smapi_model/v0/catalog/upload/presigned_upload_part.py
ask_smapi_model/v0/catalog/upload/py.typed
ask_smapi_model/v0/catalog/upload/upload_ingestion_step.py
ask_smapi_model/v0/catalog/upload/upload_status.py
ask_smapi_model/v0/development_events/__init__.py
ask_smapi_model/v0/development_events/py.typed
ask_smapi_model/v0/development_events/subscriber/__init__.py
ask_smapi_model/v0/development_events/subscriber/create_subscriber_request.py
ask_smapi_model-1.36.0.dist-info/LICENSE
ask_smapi_model-1.36.0.dist-info/METADATA
ask_smapi_model-1.36.0.dist-info/NOTICE.txt
ask_smapi_model-1.36.0.dist-info/WHEEL
ask_smapi_model-1.36.0.dist-info/top_level.txt
ask_smapi_model-1.36.0.dist-info/RECORD
