Metadata-Version: 2.1
Name: ask-smapi-model
Version: 1.36.0
Summary: The SMAPI SDK Model package provides model definitions for making Skill Management API calls.
Home-page: https://github.com/alexa/alexa-apis-for-python
Author: Alexa Skills Kit
Author-email: ask-sdk-dynamic@amazon.com
License: Apache 2.0
Keywords: SMAPI SDK,ASK SDK,Alexa Skills Kit,Alexa,Models,Smapi
Platform: UNKNOWN
Classifier: Development Status :: 5 - Production/Stable
Classifier: Intended Audience :: Developers
Classifier: Natural Language :: English
Classifier: License :: OSI Approved :: Apache Software License
Classifier: Programming Language :: Python
Classifier: Programming Language :: Python :: 2
Classifier: Programming Language :: Python :: 2.7
Classifier: Programming Language :: Python :: 3
Classifier: Programming Language :: Python :: 3.6
Requires-Python: >2.6, !=3.0.*, !=3.1.*, !=3.2.*, !=3.3.*, !=3.4.*, !=3.5.*
Requires-Dist: six (>=1.10)
Requires-Dist: ask-sdk-model-runtime (>=1.0)
Requires-Dist: enum34 ; python_version == "2.7"
Requires-Dist: typing ; python_version == "2.7"
